<?xml version="1.0" encoding="UTF-8"?>
<beans xmlns="http://www.springframework.org/schema/beans"
    xmlns:xsi="http://www.w3.org/2001/XMLSchema-instance"
    xsi:schemaLocation="
        http://www.springframework.org/schema/beans http://www.springframework.org/schema/beans/spring-beans.xsd">

    <!-- bean definitions here -->
    <!--
    <bean id="toyota" class="model.Toyota">
    	<property name="engine" ref="toyotaEngine"></property>
    </bean>
    -->
    
    <bean id="toyota" class="model.Toyota">
    	<constructor-arg ref="toyotaEngine"></constructor-arg>
    </bean>
    
    <bean id="toyotaEngine" class="model.ToyotaEngine"></bean>
    
    <bean id="kia" class="model.Kia">
	    <constructor-arg value="1000000"></constructor-arg>
	    <constructor-arg ref="toyotaEngine"></constructor-arg>
    </bean>
    
    <bean id="tesla" class="model.Tesla" autowire="byName"></bean>
    
    <bean id="engine" class="model.ToyotaEngine"></bean>
    
    <bean id="kiaEngine" class="model.KiaEngine" primary="true"></bean>

</beans>